main/__init__.py
main/album.py
main/artist.py
main/event.py
main/exceptions.py
main/handler.py
main/ratelimiter.py
main/shout.py
main/track.py
main/user.py
pyscrobble-1.2.8.dist-info/LICENSE
pyscrobble-1.2.8.dist-info/METADATA
pyscrobble-1.2.8.dist-info/WHEEL
pyscrobble-1.2.8.dist-info/top_level.txt
pyscrobble-1.2.8.dist-info/RECORD
