Metadata-Version: 2.1
Name: pyscrobble
Version: 1.2.8
Summary: A Python package for interacting with the Last.fm API
Home-page: https://github.com/opexdeveloper/pyscrobble
Author: Claqz
Author-email: lastfm@gmail.com
Classifier: Development Status :: 3 - Alpha
Classifier: Intended Audience :: Developers
Classifier: License :: OSI Approved :: MIT License
Classifier: Programming Language :: Python :: 3
Classifier: Programming Language :: Python :: 3.9
Classifier: Programming Language :: Python :: 3.10
Classifier: Programming Language :: Python :: 3.11
Classifier: Programming Language :: Python :: 3.12
Classifier: Programming Language :: Python :: 3 :: Only
Classifier: Programming Language :: Python :: Implementation :: CPython
Requires-Python: >=3.9
License-File: LICENSE
Requires-Dist: requests>=2.25.1
Requires-Dist: xmltodict>=0.12.0
Provides-Extra: dev
Requires-Dist: pytest>=6.2.5; extra == "dev"
Requires-Dist: flake8>=3.9.2; extra == "dev"
